fds/__init__.py
fds/sdk/__init__.py
fds/sdk/ConversationalAPIPoweredbyFactSetMercury/__init__.py
fds/sdk/ConversationalAPIPoweredbyFactSetMercury/api_client.py
fds/sdk/ConversationalAPIPoweredbyFactSetMercury/configuration.py
fds/sdk/ConversationalAPIPoweredbyFactSetMercury/exceptions.py
fds/sdk/ConversationalAPIPoweredbyFactSetMercury/model_utils.py
fds/sdk/ConversationalAPIPoweredbyFactSetMercury/rest.py
fds/sdk/ConversationalAPIPoweredbyFactSetMercury/api/__init__.py
fds/sdk/ConversationalAPIPoweredbyFactSetMercury/api/chat_api.py
fds/sdk/ConversationalAPIPoweredbyFactSetMercury/api/download_api.py
fds/sdk/ConversationalAPIPoweredbyFactSetMercury/api/feedback_api.py
fds/sdk/ConversationalAPIPoweredbyFactSetMercury/apis/__init__.py
fds/sdk/ConversationalAPIPoweredbyFactSetMercury/model/__init__.py
fds/sdk/ConversationalAPIPoweredbyFactSetMercury/model/adaptive_card.py
fds/sdk/ConversationalAPIPoweredbyFactSetMercury/model/bad_feedback_request_error.py
fds/sdk/ConversationalAPIPoweredbyFactSetMercury/model/bad_feedback_request_error_object.py
fds/sdk/ConversationalAPIPoweredbyFactSetMercury/model/bad_request_error.py
fds/sdk/ConversationalAPIPoweredbyFactSetMercury/model/bad_request_error_object.py
fds/sdk/ConversationalAPIPoweredbyFactSetMercury/model/bad_request_error_with_invalid_data_schema.py
fds/sdk/ConversationalAPIPoweredbyFactSetMercury/model/bad_request_error_with_invalid_data_schema_object.py
fds/sdk/ConversationalAPIPoweredbyFactSetMercury/model/chat_polling_request.py
fds/sdk/ConversationalAPIPoweredbyFactSetMercury/model/chat_polling_request_data.py
fds/sdk/ConversationalAPIPoweredbyFactSetMercury/model/citations.py
fds/sdk/ConversationalAPIPoweredbyFactSetMercury/model/download.py
fds/sdk/ConversationalAPIPoweredbyFactSetMercury/model/federation_data.py
fds/sdk/ConversationalAPIPoweredbyFactSetMercury/model/feedback_request.py
fds/sdk/ConversationalAPIPoweredbyFactSetMercury/model/feedback_request_data.py
fds_sdk_conversationalapipoweredbyfactsetmercury-1.2.2.dist-info/licenses/LICENSE
fds_sdk_conversationalapipoweredbyfactsetmercury-1.2.2.dist-info/METADATA
fds_sdk_conversationalapipoweredbyfactsetmercury-1.2.2.dist-info/WHEEL
fds_sdk_conversationalapipoweredbyfactsetmercury-1.2.2.dist-info/top_level.txt
fds_sdk_conversationalapipoweredbyfactsetmercury-1.2.2.dist-info/RECORD
